edc_phq9/__init__.py
edc_phq9/admin.py
edc_phq9/admin_site.py
edc_phq9/apps.py
edc_phq9/auth_objects.py
edc_phq9/auths.py
edc_phq9/choices.py
edc_phq9/constants.py
edc_phq9/fieldsets.py
edc_phq9/forms.py
edc_phq9/model_admin_mixins.py
edc_phq9/model_mixins.py
edc_phq9/models.py
edc_phq9/urls.py
edc_phq9/utils.py
edc_phq9-1.3.1.dist-info/licenses/LICENSE
edc_phq9-1.3.1.dist-info/WHEEL
edc_phq9-1.3.1.dist-info/METADATA
edc_phq9-1.3.1.dist-info/RECORD
